flickr_download/__init__.py
flickr_download/filename_handlers.py
flickr_download/flick_download.py
flickr_download/logging_utils.py
flickr_download/py.typed
flickr_download/utils.py
flickr_download-0.3.7.dist-info/LICENSE
flickr_download-0.3.7.dist-info/METADATA
flickr_download-0.3.7.dist-info/WHEEL
flickr_download-0.3.7.dist-info/entry_points.txt
flickr_download-0.3.7.dist-info/RECORD
