Metadata-Version: 2.1
Name: flickr-download
Version: 0.3.7
Summary: Download photos from Flickr
Home-page: https://github.com/beaufour/flickr-download
License: Apache-2.0
Author: Allan Beaufour
Author-email: allan@beaufour.dk
Requires-Python: >=3.9,<4.0
Classifier: License :: OSI Approved :: Apache Software License
Classifier: Programming Language :: Python :: 3
Classifier: Programming Language :: Python :: 3.9
Classifier: Programming Language :: Python :: 3.10
Classifier: Programming Language :: Python :: 3.11
Classifier: Programming Language :: Python :: 3.12
Requires-Dist: PyYAML (>=5.3,<7.0)
Requires-Dist: flickr-api (>=0.7.7,<0.8.0)
Requires-Dist: importlib-metadata (>=4.2.0,<4.3.0) ; python_version < "3.8"
Requires-Dist: interrogate (>=1.5.0,<2.0.0)
Requires-Dist: pathvalidate (>=2.5.2,<4.0.0)
Requires-Dist: python-dateutil (>=2.8.1,<3.0.0)
Requires-Dist: setuptools (>=75.1.0,<76.0.0)
Requires-Dist: usingversion (>=0.1.2,<0.2.0)
Project-URL: Repository, https://github.com/beaufour/flickr-download
